assertthat_bdd/__init__.py
assertthat_bdd/jira_integration.py
assertthat_bdd-1.2.0.dist-info/LICENSE.txt
assertthat_bdd-1.2.0.dist-info/METADATA
assertthat_bdd-1.2.0.dist-info/WHEEL
assertthat_bdd-1.2.0.dist-info/top_level.txt
assertthat_bdd-1.2.0.dist-info/RECORD
